[
    {
        "name": "Lilly Saw",
        "pic": "user1",
        "register": "Feb 10,2022",
        "country": "india",
        "usage": 50,
        "payment": "visa",
        "activity": "10sec"
    },
    {
        "name": "John Hofman",
        "pic": "user2",
        "register": "Jan 10,2022",
        "country": "us",
        "usage": 20,
        "payment": "paypal",
        "activity": "10hrs"
    },
    {
        "name": "Raju Paul",
        "pic": "user3",
        "register": "Feb 20,2022",
        "country": "india",
        "usage": 80,
        "payment": "visa",
        "activity": "10sec"
    },
    {
        "name": "Larry Saw",
        "pic": "user4",
        "register": "Feb 10,2022",
        "country": "canada",
        "usage": 90,
        "payment": "paypal",
        "activity": "20hrs"
    },
    {
        "name": "Paul WInkel",
        "pic": "user5",
        "register": "Feb 20,2022",
        "country": "russia",
        "usage": 70,
        "payment": "visa",
        "activity": "1sec"
    },
    {
        "name": "Masud Hossen",
        "pic": "user6",
        "register": "Feb 10,2022",
        "country": "bangladesh",
        "usage": 100,
        "payment": "visa",
        "activity": "10sec"
    },
    {
        "name": "Tom Sawyer",
        "pic": "user7",
        "register": "Feb 30,2022",
        "country": "brazil",
        "usage": 50,
        "payment": "visa",
        "activity": "10sec"
    },
    {
        "name": "Muskan Saw",
        "pic": "user1",
        "register": "Feb 10,2022",
        "country": "us",
        "usage": 50,
        "payment": "visa",
        "activity": "2sec"
    }
]

